odoo/addons/website_event_require_login/README.rst
odoo/addons/website_event_require_login/__init__.py
odoo/addons/website_event_require_login/__manifest__.py
odoo/addons/website_event_require_login/controllers/__init__.py
odoo/addons/website_event_require_login/controllers/main.py
odoo/addons/website_event_require_login/i18n/ca.po
odoo/addons/website_event_require_login/i18n/de.po
odoo/addons/website_event_require_login/i18n/es.po
odoo/addons/website_event_require_login/i18n/fi.po
odoo/addons/website_event_require_login/i18n/fi_FI.po
odoo/addons/website_event_require_login/i18n/fr.po
odoo/addons/website_event_require_login/i18n/it.po
odoo/addons/website_event_require_login/i18n/pt.po
odoo/addons/website_event_require_login/i18n/website_event_require_login.pot
odoo/addons/website_event_require_login/models/__init__.py
odoo/addons/website_event_require_login/models/event.py
odoo/addons/website_event_require_login/readme/CONFIGURE.md
odoo/addons/website_event_require_login/readme/CONTRIBUTORS.md
odoo/addons/website_event_require_login/readme/DESCRIPTION.md
odoo/addons/website_event_require_login/readme/ROADMAP.md
odoo/addons/website_event_require_login/readme/USAGE.md
odoo/addons/website_event_require_login/static/description/icon.png
odoo/addons/website_event_require_login/static/description/index.html
odoo/addons/website_event_require_login/views/event_views.xml
odoo/addons/website_event_require_login/views/website_event_templates.xml
odoo_addon_website_event_require_login-17.0.1.0.0.6.dist-info/METADATA
odoo_addon_website_event_require_login-17.0.1.0.0.6.dist-info/WHEEL
odoo_addon_website_event_require_login-17.0.1.0.0.6.dist-info/top_level.txt
odoo_addon_website_event_require_login-17.0.1.0.0.6.dist-info/RECORD
