Metadata-Version: 2.1
Name: odoo-addon-website_event_require_login
Version: 17.0.1.0.0.6
Requires-Python: >=3.10
Requires-Dist: odoo>=17.0a,<17.1dev
Summary: Website Event Require Login
Home-page: https://github.com/OCA/event
License: AGPL-3
Author: Tecnativa, Odoo Community Association (OCA)
Author-email: support@odoo-community.org
Classifier: Programming Language :: Python
Classifier: Framework :: Odoo
Classifier: Framework :: Odoo :: 17.0
Classifier: License :: OSI Approved :: GNU Affero General Public License v3
